programmable_cellular_machine/__init__.py
programmable_cellular_machine/hight/__init__.py
programmable_cellular_machine/hight/hight_load.py
programmable_cellular_machine/hight/places.py
programmable_cellular_machine/hight/rules.py
programmable_cellular_machine/iterators.py
programmable_cellular_machine/machine.py
programmable_cellular_machine/palette.py
programmable_cellular_machine/places.py
programmable_cellular_machine/rules.py
programmable_cellular_machine/utils.py
programmable_cellular_machine/visual.py
programmable_cellular_machine-0.0.4.dist-info/LICENSE
programmable_cellular_machine-0.0.4.dist-info/WHEEL
programmable_cellular_machine-0.0.4.dist-info/METADATA
programmable_cellular_machine-0.0.4.dist-info/RECORD
